{
  "kind": "singleType",
  "collectionName": "footers",
  "info": {
    "singularName": "footer",
    "pluralName": "footers",
    "displayName": "09 - Footer",
    "description": ""
  },
  "options": {
    "draftAndPublish": false
  },
  "pluginOptions": {
    "i18n": {
      "localized": true
    }
  },
  "attributes": {
    "address": {
      "pluginOptions": {
        "i18n": {
          "localized": true
        }
      },
      "type": "string",
      "required": true
    },
    "contactFooter": {
      "displayName": "Contact-Footer",
      "type": "component",
      "repeatable": true,
      "pluginOptions": {
        "i18n": {
          "localized": true
        }
      },
      "component": "contact-footer.contact-footer",
      "required": true
    },
    "linksFooter": {
      "displayName": "Links-footer",
      "type": "component",
      "repeatable": true,
      "pluginOptions": {
        "i18n": {
          "localized": true
        }
      },
      "component": "links-footer.links-footer",
      "required": false
    },
    "hotelsName": {
      "displayName": "Hotels-name",
      "type": "component",
      "repeatable": true,
      "pluginOptions": {
        "i18n": {
          "localized": true
        }
      },
      "component": "hotels-name.hotels-name"
    },
    "footer": {
      "type": "component",
      "repeatable": true,
      "pluginOptions": {
        "i18n": {
          "localized": true
        }
      },
      "component": "links-footer.links-footer"
    },
    "labelIcons": {
      "displayName": "Label-icons",
      "type": "component",
      "repeatable": true,
      "pluginOptions": {
        "i18n": {
          "localized": true
        }
      },
      "component": "label-icons.label-icons",
      "required": true
    }
  }
}
